{
    "English": "vosk-model-small-en-us-0.15",
    "Indian English": "vosk-model-small-en-in-0.4",
    "Chinese": "vosk-model-small-cn-0.22",
    "Russian": "vosk-model-small-ru-0.22",
    "French": "vosk-model-small-fr-0.22",
    "French (pguyot)": "vosk-model-small-fr-pguyot-0.3",
    "German": "vosk-model-small-de-0.15",
    "Spanish": "vosk-model-small-es-0.42",
    "Portuguese": "vosk-model-small-pt-0.3",
    "Turkish": "vosk-model-small-tr-0.3",
    "Vietnamese": "vosk-model-small-vn-0.3",
    "Italian": "vosk-model-small-it-0.22",
    "Dutch": "vosk-model-small-nl-0.22",
    "Catalan": "vosk-model-small-ca-0.4",
    "Farsi": "vosk-model-small-fa-0.5",
    "Ukrainian": "vosk-model-small-uk-v3-nano",
    "Kazakh": "vosk-model-small-kz-0.15",
    "Swedish": "vosk-model-small-sv-rhasspy-0.15",
    "Japanese": "vosk-model-small-ja-0.22",
    "Esperanto": "vosk-model-small-eo-0.42",
    "Hindi": "vosk-model-small-hi-0.22",
    "Czech": "vosk-model-small-cs-0.4-rhasspy",
    "Uzbek": "vosk-model-small-uz-0.22",
    "Korean": "vosk-model-small-ko-0.22"
}